odoo/addons/stock_valuation_no_developer_mode/README.rst
odoo/addons/stock_valuation_no_developer_mode/__init__.py
odoo/addons/stock_valuation_no_developer_mode/__manifest__.py
odoo/addons/stock_valuation_no_developer_mode/i18n/stock_valuation_no_developer_mode.pot
odoo/addons/stock_valuation_no_developer_mode/readme/CONTRIBUTORS.rst
odoo/addons/stock_valuation_no_developer_mode/readme/DESCRIPTION.rst
odoo/addons/stock_valuation_no_developer_mode/static/description/icon.png
odoo/addons/stock_valuation_no_developer_mode/static/description/index.html
odoo/addons/stock_valuation_no_developer_mode/views/stock_valuation_layer.xml
odoo14_addon_stock_valuation_no_developer_mode-14.0.1.0.1.dist-info/METADATA
odoo14_addon_stock_valuation_no_developer_mode-14.0.1.0.1.dist-info/WHEEL
odoo14_addon_stock_valuation_no_developer_mode-14.0.1.0.1.dist-info/top_level.txt
odoo14_addon_stock_valuation_no_developer_mode-14.0.1.0.1.dist-info/RECORD
